panku/__init__.py
panku/panku.py
panku-0.7.data/scripts/panku
panku-0.7.dist-info/LICENSE
panku-0.7.dist-info/METADATA
panku-0.7.dist-info/WHEEL
panku-0.7.dist-info/top_level.txt
panku-0.7.dist-info/RECORD
