Metadata-Version: 2.1
Name: panku
Version: 0.7
Summary: Easy API-less reddit scraper
Home-page: UNKNOWN
Author: Skynse
Author-email: 
License: MIT
Platform: UNKNOWN
Requires-Python: >=3.6
